<?xml version="1.0" encoding="UTF-8"?>
<FreeMarsImageConfiguration>
    <imagesFolder>/images/</imagesFolder>
    <images>
        <image>
            <name>METEOR</name>
            <path>message/meteor.png</path>
        </image>
        <image>
            <name>OXYGEN</name>
            <path>message/oxygen.png</path>
        </image>
        <image>
            <name>HYDROGEN</name>
            <path>message/hydrogen.png</path>
        </image>
        <image>
            <name>FIRE</name>
            <path>message/fire.png</path>
        </image>
        <image>
            <name>TRANSPORTER_ACCIDENT_EVENT</name>
            <path>message/transporter_accident_event.png</path>
        </image>
        <image>
            <name>SHUTTLE_ACCIDENT_EVENT</name>
            <path>message/shuttle_accident_event.png</path>
        </image>
        <image>
            <name>COLONISTS_RETURNING_TO_EARTH</name>
            <path>message/colonists_returning_to_earth_event.png</path>
        </image>
        <image>
            <name>FREE_COLONISTS_EVENT</name>
            <path>message/free_colonists_event.png</path>
        </image>
        <image>
            <name>CREDIT_DONATION_EVENT</name>
            <path>message/credit_donation.png</path>
        </image>
        <image>
            <name>FERTILIZER_DONATION_EVENT</name>
            <path>message/fertilizer_donation.png</path>
        </image>
        <image>
            <name>WATER_LEAK_EVENT</name>
            <path>message/water_leak.png</path>
        </image>
        <image>
            <name>FOOD_CONTAMINATION_EVENT</name>
            <path>message/food_contamination.png</path>
        </image>
        <image>
            <name>ENERGY_LOSS_EVENT</name>
            <path>message/energy_loss.png</path>
        </image>
        <image>
            <name>MINING_ACCIDENT</name>
            <path>message/mining_accident.png</path>
        </image>
    </images>
</FreeMarsImageConfiguration>